README.txt
bootstrap.py
buildout.cfg
setup.cfg
setup.py
collective/__init__.py
collective.z3cform.kss.egg-info/PKG-INFO
collective.z3cform.kss.egg-info/SOURCES.txt
collective.z3cform.kss.egg-info/dependency_links.txt
collective.z3cform.kss.egg-info/entry_points.txt
collective.z3cform.kss.egg-info/namespace_packages.txt
collective.z3cform.kss.egg-info/not-zip-safe
collective.z3cform.kss.egg-info/requires.txt
collective.z3cform.kss.egg-info/top_level.txt
collective/z3cform/__init__.py
collective/z3cform/kss/README.txt
collective/z3cform/kss/__init__.py
collective/z3cform/kss/configure.zcml
collective/z3cform/kss/form.pt
collective/z3cform/kss/form.py
collective/z3cform/kss/overrides.zcml
collective/z3cform/kss/test.py
collective/z3cform/kss/kss/__init__.py
collective/z3cform/kss/kss/configure.zcml
collective/z3cform/kss/kss/form.kss
collective/z3cform/kss/kss/validation.py
collective/z3cform/kss/tests/__init__.py
collective/z3cform/kss/tests/test_all.py
docs/HISTORY.txt