Metadata-Version: 1.0
Name: collective.z3cform.kss
Version: 0.1b1dev
Summary: enable inline validation with z3c form
Home-page: http://svn.plone.org/svn/collective/collective.z3cform.kss/trunk/
Author: Jean-Francois Roche
Author-email: jfroche@affinitic.be
License: GPL
Platform: UNKNOWN
Classifier: Programming Language :: Python
Classifier: Topic :: Software Development :: Libraries :: Python Modules
